sqlgen/__init__.py
sqlgen/exc.py
sqlgen/helpers.py
sqlgen/joins.py
sqlgen/utils.py
sqlgen/repository/__init__.py
sqlgen/repository/bases/__init__.py
sqlgen/repository/bases/constrained.py
sqlgen/repository/bases/database_repository.py
sqlgen/repository/bases/object_bound.py
sqlgen/repository/impl/__init__.py
sqlgen/repository/impl/async_constrained.py
sqlgen/repository/impl/async_object_bound.py
sqlgen/repository/impl/asynchronous.py
sqlgen/repository/impl/synchronous.py
sqlgen/repository/impl/synchronous_constrained.py
sqlgen/statement_executor/__init__.py
sqlgen/statement_executor/asynchronous.py
sqlgen/statement_executor/synchronous.py
sqlgen/statement_generator/__init__.py
sqlgen/statement_generator/base.py
sqlgen/statement_generator/constrained.py
sqlgen/statement_generator/exc.py
sqlgen/statement_generator/factories.py
sqlgen/statement_generator/object_bound.py
sql_repository_generator-1.2.0.dist-info/LICENSE
sql_repository_generator-1.2.0.dist-info/METADATA
sql_repository_generator-1.2.0.dist-info/WHEEL
sql_repository_generator-1.2.0.dist-info/top_level.txt
sql_repository_generator-1.2.0.dist-info/RECORD
