Metadata-Version: 2.1
Name: sql-repository-generator
Version: 1.2.0
Summary: Library to generate repository for SQLAlchemy based on ORM Models
Author-email: Baboin Arthur <baboin.arthur@gmail.com>
Project-URL: Homepage, https://gitlab.com/Tagashy/sqlgen
Project-URL: Documentation, https://tagashy.gitlab.io/sqlgen/
Project-URL: Repository, https://gitlab.com/Tagashy/sqlgen.git
Project-URL: Issues, https://gitlab.com/Tagashy/sqlgen/issues
Project-URL: Bug Tracker, https://gitlab.com/Tagashy/easysql/issues
Keywords: sql,sqlalchemy,repository,generator
Classifier: Development Status :: 4 - Beta
Classifier: Intended Audience :: Developers
Classifier: Topic :: Software Development :: Code Generators
Classifier: Topic :: Software Development :: Libraries
Classifier: Framework :: AsyncIO
Classifier: Programming Language :: Python :: 3.12
Classifier: License :: OSI Approved :: MIT License
Classifier: Operating System :: OS Independent
Requires-Python: >=3.12
License-File: LICENSE
Requires-Dist: SQLAlchemy~=2.0.23
Provides-Extra: tests
Requires-Dist: pytest~=8.0.2; extra == "tests"
Requires-Dist: pytest-mock~=3.12.0; extra == "tests"
Requires-Dist: pytest-faker~=2.0.0; extra == "tests"
Requires-Dist: pytest-cov~=4.1.0; extra == "tests"
Requires-Dist: pytest-unordered~=0.5.2; extra == "tests"
Requires-Dist: pytest-asyncio~=0.23.2; extra == "tests"
Requires-Dist: EasyFactory~=1.4.2; extra == "tests"
Requires-Dist: aiosqlite==0.19.0; extra == "tests"
Requires-Dist: gevent~=24.2.1; extra == "tests"
